MLapp/README.txt
MLapp/__init__.py
MLapp/app.py
MLapp/generateScript.py
MLapp/helperFunctions.py
MLapp/launcher.py
MLapp/main.py
MLapp/scriptTemplate.py
MLapp/subScript.py
MLapp/UI/__init__.py
MLapp/UI/autoML.py
MLapp/UI/classifcationAlgo.py
MLapp/UI/componentIDs.py
MLapp/UI/dataSampling.py
MLapp/UI/featureSelection.py
MLapp/UI/layouts.py
MLapp/UI/modelEvaluation.py
MLapp/UI/result.py
MLapp/UI/scaling.py
MLapp/UI/submit.py
MLapp/UI/uploadInput.py
MLapp1-0.0.37.dist-info/LICENSE.toml
MLapp1-0.0.37.dist-info/METADATA
MLapp1-0.0.37.dist-info/WHEEL
MLapp1-0.0.37.dist-info/top_level.txt
MLapp1-0.0.37.dist-info/RECORD
